funvideo/app/__init__.py
funvideo/app/asgi.py
funvideo/app/main.py
funvideo/app/router.py
funvideo/app/config/__init__.py
funvideo/app/config/bak.py
funvideo/app/config/core.py
funvideo/app/controllers/base.py
funvideo/app/controllers/ping.py
funvideo/app/controllers/manager/base_manager.py
funvideo/app/controllers/manager/memory_manager.py
funvideo/app/controllers/manager/redis_manager.py
funvideo/app/controllers/v1/base.py
funvideo/app/controllers/v1/llm.py
funvideo/app/controllers/v1/video.py
funvideo/app/models/__init__.py
funvideo/app/models/const.py
funvideo/app/models/exception.py
funvideo/app/models/schema.py
funvideo/app/services/__init__.py
funvideo/app/services/llm.py
funvideo/app/services/state.py
funvideo/app/services/subtitle.py
funvideo/app/services/task.py
funvideo/app/services/video.py
funvideo/app/services/voice2.py
funvideo/app/utils/__init__.py
funvideo/app/utils/utils.py
funvideo/webui/Main.py
funvideo-1.0.24.dist-info/METADATA
funvideo-1.0.24.dist-info/WHEEL
funvideo-1.0.24.dist-info/top_level.txt
funvideo-1.0.24.dist-info/RECORD
