Metadata-Version: 2.1
Name: funvideo
Version: 1.0.24
Summary: funvideo
Author-email: niuliangtao <farfarfun@qq.com>
Requires-Python: >=3.9
Requires-Dist: edge-tts~=6.1.10
Requires-Dist: faster-whisper>=1.1.0
Requires-Dist: funai>=1.0.1
Requires-Dist: funtalk>=1.0.11
Requires-Dist: moviepy>=2.0.0
Requires-Dist: openai>=1.54.5
